merlin_ai/__init__.py
merlin_ai/ai_classes.py
merlin_ai/data_classes.py
merlin_ai/decorators.py
merlin_ai/llm_classes.py
merlin_ai/settings.py
merlin_ai-1.0.0.dist-info/METADATA
merlin_ai-1.0.0.dist-info/WHEEL
merlin_ai-1.0.0.dist-info/RECORD
