Metadata-Version: 2.1
Name: merlin-ai
Version: 1.0.0
Summary: 
Home-page: https://github.com/matevzpoljanc/merlin-ai
License: MIT
Author: Matevz Poljanc
Requires-Python: >=3.9,<4.0
Classifier: License :: OSI Approved :: MIT License
Classifier: Programming Language :: Python :: 3
Classifier: Programming Language :: Python :: 3.9
Classifier: Programming Language :: Python :: 3.10
Classifier: Programming Language :: Python :: 3.11
Requires-Dist: litellm (>=1.55.3,<2.0.0)
Requires-Dist: tiktoken (>=0.8.0,<0.9.0)
Project-URL: Repository, https://github.com/matevzpoljanc/merlin-ai
